openqasm_pygments/__init__.py
openqasm_pygments/_lexeme.py
openqasm_pygments/exceptions.py
openqasm_pygments/openpulse.py
openqasm_pygments/py.typed
openqasm_pygments/qasm2.py
openqasm_pygments/qasm3.py
openqasm_pygments-0.2.0.dist-info/licenses/LICENSE
openqasm_pygments-0.2.0.dist-info/METADATA
openqasm_pygments-0.2.0.dist-info/WHEEL
openqasm_pygments-0.2.0.dist-info/entry_points.txt
openqasm_pygments-0.2.0.dist-info/top_level.txt
openqasm_pygments-0.2.0.dist-info/RECORD
