Metadata-Version: 2.4
Name: openqasm-pygments
Version: 0.2.0
Summary: Pygments tools for OpenQASM
Home-page: https://openqasm.github.io/openqasm-pygments
Author: OpenQASM contributors
License: Apache 2.0 License
Project-URL: Bug Tracker, https://github.com/openqasm/openqasm-pygments/issues
Project-URL: Documentation, https://openqasm.github.com/openqasm-pygments
Project-URL: Source Code, https://github.com/openqasm/openqasm-pygments
License-File: LICENSE
Requires-Dist: Pygments~=2.0
Provides-Extra: all
Dynamic: license-file
